MANIFEST.in
README.md
requirements.txt
setup.cfg
setup.py
versioneer.py
botcity/plugins/googledrive/__init__.py
botcity/plugins/googledrive/_version.py
botcity/plugins/googledrive/plugin.py
botcity_googledrive_plugin.egg-info/PKG-INFO
botcity_googledrive_plugin.egg-info/SOURCES.txt
botcity_googledrive_plugin.egg-info/dependency_links.txt
botcity_googledrive_plugin.egg-info/requires.txt
botcity_googledrive_plugin.egg-info/top_level.txt
tests/test_import.py
tests/test_plugin.py