Metadata-Version: 2.1
Name: botcity-googledrive-plugin
Version: 0.4.0
Home-page: https://bitbucket.org/botcitydev/bot-googledrive-plugin-python.git
Requires-Python: >=3.7
Requires-Dist: google-api-python-client
Requires-Dist: google-auth-oauthlib
Requires-Dist: google-auth-httplib2
